icemac.songbeamer-1.0-py2.7-nspkg.pth
icemac/songbeamer/USAGE.rst
icemac/songbeamer/__init__.py
icemac/songbeamer/sng.py
icemac/songbeamer/xls.py
icemac/songbeamer/tests/__init__.py
icemac/songbeamer/tests/example.sng
icemac/songbeamer/tests/test_sng.py
icemac/songbeamer/tests/test_xls.py
icemac.songbeamer-1.0.dist-info/DESCRIPTION.rst
icemac.songbeamer-1.0.dist-info/METADATA
icemac.songbeamer-1.0.dist-info/RECORD
icemac.songbeamer-1.0.dist-info/WHEEL
icemac.songbeamer-1.0.dist-info/entry_points.txt
icemac.songbeamer-1.0.dist-info/metadata.json
icemac.songbeamer-1.0.dist-info/namespace_packages.txt
icemac.songbeamer-1.0.dist-info/top_level.txt
