Metadata-Version: 2.0
Name: icemac.songbeamer
Version: 1.0
Summary: Python 3 library to import from and export to SongBeamer format.
Home-page: https://github.com/icemac/icemac.songbeamer
Author: Michael Howitz
Author-email: icemac@gmx.net
License: MIT
Keywords: python 3 songbeamer import export
Platform: UNKNOWN
Classifier: Development Status :: 4 - Beta
Classifier: Intended Audience :: Developers
Classifier: Intended Audience :: Religion
Classifier: License :: OSI Approved
Classifier: License :: OSI Approved :: MIT License
Classifier: Natural Language :: English
Classifier: Operating System :: OS Independent
Classifier: Programming Language :: Python
Classifier: Programming Language :: Python :: 3 :: Only
Classifier: Programming Language :: Python :: 3
Classifier: Programming Language :: Python :: 3.7
Classifier: Programming Language :: Python :: Implementation
Classifier: Programming Language :: Python :: Implementation :: CPython
Classifier: Topic :: Software Development
Classifier: Topic :: Software Development :: Libraries
Classifier: Topic :: Software Development :: Libraries :: Python Modules
Classifier: Topic :: Text Processing
Classifier: Topic :: Text Processing :: Filters
Classifier: Topic :: Religion
Provides-Extra: test
Provides-Extra: xls
Requires-Dist: setuptools
Provides-Extra: test
Requires-Dist: pytest; extra == 'test'
Requires-Dist: xlrd; extra == 'test'
Provides-Extra: xls
Requires-Dist: xlwt; extra == 'xls'
